{
    "title": "E-Bike Safety Tips for Riders",
    "description": "Stay safe while riding your e-bike with these essential safety tips, including wearing protective gear and following traffic rules.",
    "sources": [
        {
            "title": "Illinois Bicycle Rules of the Road 2024",
            "link": "https://www.ilsos.gov/publications/pdf_publications/dsd_a143.pdf"
        },
        {
            "title": "NYC DOT - Bike Smart",
            "link": "http://nyc.gov/bikesmart"
        },
        {
            "title": "Kids and Bicycle Safety",
            "link": "https://one.nhtsa.gov/people/injury/pedbimot/bike/kidsandbikesafetyweb/index.htm"
        }
    ],
    "index": 6.0,
    "article_plan": "# E-Bike Safety Tips for Riders\n\n## Introduction\n- Brief overview of the increasing popularity of e-bikes and the importance of safety while riding.\n\n## 1. Wear Protective Gear\n- Importance of wearing a helmet, gloves, and other protective gear while riding an e-bike.\n- Tips on choosing the right gear for maximum protection.\n\n## 2. Follow Traffic Rules\n- Explanation of the importance of following traffic rules while riding an e-bike.\n- Tips on how to navigate traffic safely and effectively.\n\n## 3. Be Visible\n- Importance of being visible to other road users while riding an e-bike.\n- Tips on using lights, reflectors, and bright clothing to increase visibility.\n\n## 4. Maintain Your E-Bike\n- Importance of regular maintenance to ensure your e-bike is safe to ride.\n- Tips on checking brakes, tires, and other components for optimal performance.\n\n## 5. Ride Defensively\n- Explanation of defensive riding techniques to stay safe on the road.\n- Tips on anticipating potential hazards and reacting accordingly.\n\n## Conclusion\n- Recap of the essential safety tips for riding an e-bike.\n- Encouragement to prioritize safety while enjoying the benefits of e-bike riding."
}