{
    "title": "Review of Samsung Galaxy Tab A9+ 128GB, Graphite, Tablet, 3 Year Manufacturer Extended Warranty (UK Version)",
    "description": "This is a product review of the Review of Samsung Galaxy Tab A9+ 128GB, Graphite, Tablet, 3 Year Manufacturer Extended Warranty (UK Version).",
    "sources": [
        {
            "title": "Samsung Galaxy Tab A9+ 128GB, Blue, Tablet, 3 Year Manufacturer ...",
            "link": "https://www.amazon.co.uk/Samsung-Wifi-128GB-Blue-Warranty/dp/B0CMDS33N4"
        },
        {
            "title": "Amazon.com : SAMSUNG Galaxy Tab A9+ 11\u201d 128GB Android ...",
            "link": "https://www.amazon.com/SAMSUNG-Android-Speakers-Upgraded-Chipset/dp/B0CLF4NVSL"
        },
        {
            "title": "Samsung Galaxy Tab A9+ 128GB, Graphite, Tablet, 3 Year ...",
            "link": "https://www.amazon.co.uk/Samsung-Graphite-Manufacturer-Extended-Warranty/dp/B0CMD9WY1D"
        }
    ],
    "index": 0,
    "article_plan": "# Review of Samsung Galaxy Tab A9+ 128GB, Graphite, Tablet, 3 Year Manufacturer Extended Warranty (UK Version)\n\n## Introduction\nBrief overview of the Samsung Galaxy Tab A9+ 128GB tablet and its features. Mention the extended warranty and its importance.\n\n## Design and Build Quality\nDiscuss the design and build quality of the tablet, including the materials used, dimensions, and weight. Mention any unique features or design elements.\n\n## Display and Performance\nEvaluate the display quality of the tablet, including resolution, color accuracy, and brightness. Discuss the performance of the device, including speed, responsiveness, and multitasking capabilities.\n\n## Storage and Battery Life\nReview the storage capacity of the tablet and its ability to store large files and apps. Evaluate the battery life of the device and its performance under normal usage.\n\n## Camera and Audio Quality\nDiscuss the camera quality of the tablet, including the resolution and features. Evaluate the audio quality of the device, including speaker performance and headphone jack.\n\n## Software and User Interface\nReview the software of the tablet, including the operating system and any pre-installed apps. Evaluate the user interface of the device and its ease of use.\n\n## Warranty and Customer Support\nDiscuss the importance of the extended warranty included with the tablet and how it benefits the customer. Evaluate the customer support provided by Samsung for UK customers.\n\n## Conclusion\nSummarize the key points of the review and provide a final recommendation for potential buyers. Mention any standout features or drawbacks of the Samsung Galaxy Tab A9+ 128GB tablet."
}